ReviewerParser/__init__.py
reviewer_generator-0.0.6.dist-info/LICENSE
reviewer_generator-0.0.6.dist-info/METADATA
reviewer_generator-0.0.6.dist-info/WHEEL
reviewer_generator-0.0.6.dist-info/top_level.txt
reviewer_generator-0.0.6.dist-info/RECORD
