Metadata-Version: 2.1
Name: reviewer-generator
Version: 0.0.6
Summary: Terminal-based test reviewer generator on formatted notes
Home-page: https://github.com/shshshshshan/reviewer-generator
Author: Shan Seneca
Author-email: shnmyklsnc@gmail.com
Project-URL: Bug Tracker, https://github.com/shshshshshan/reviewer-generator/issues
Classifier: Programming Language :: Python :: 3
Classifier: License :: OSI Approved :: MIT License
Classifier: Operating System :: OS Independent
Requires-Python: >=3.11
License-File: LICENSE
